{
  "id": "quiz-Process-Selection-Manufacturing",
  "title": "Process Selection (Manufacturing)",
  "description": "Assesses analytical and critical understanding of manufacturing process selection, process characteristics, product–process matrix, process analysis, break-even analysis, and business process reengineering.",
  "subject": "DSC2370 - Operations Management",
  "totalQuestions": 40,
  "essayQuestions": 2,
  "difficulty": "Moderate to High",
  "questions": [
    {
      "id": "q1",
      "type": "multipleChoice",
      "question": "Why is process selection considered a strategic decision rather than an operational one?",
      "options": [
        "Because it focuses only on daily scheduling decisions",
        "Because it determines the long-term cost structure and flexibility of the operation",
        "Because it is reversible without major investment",
        "Because it affects marketing decisions only"
      ],
      "answer": "Because it determines the long-term cost structure and flexibility of the operation",
      "marks": 2
    },
    {
      "id": "q2",
      "type": "multipleChoice",
      "question": "Which combination of process characteristics is MOST likely to result in the lowest unit processing cost?",
      "options": [
        "Low volume, high variety, high visibility",
        "High volume, low variety, low visibility",
        "Low volume, low variety, high variation",
        "High variety, high customer contact"
      ],
      "answer": "High volume, low variety, low visibility",
      "marks": 2
    },
    {
      "id": "q3",
      "type": "multipleChoice",
      "question": "In a project process, which feature creates the greatest management challenge?",
      "options": [
        "High equipment specialization",
        "High repetition of tasks",
        "Uniqueness and complexity of each output",
        "Short production time horizons"
      ],
      "answer": "Uniqueness and complexity of each output",
      "marks": 2
    },
    {
      "id": "q4",
      "type": "multipleChoice",
      "question": "Which statement best differentiates a jobbing process from a batch process?",
      "options": [
        "Jobbing processes have higher volumes than batch processes",
        "Batch processes involve greater customization than jobbing processes",
        "Batch processes produce repeated outputs in identifiable lots",
        "Jobbing processes rely on dedicated assembly lines"
      ],
      "answer": "Batch processes produce repeated outputs in identifiable lots",
      "marks": 2
    },
    {
      "id": "q5",
      "type": "multipleChoice",
      "question": "Why are mass processes positioned between batch and continuous processes on the volume–variety continuum?",
      "options": [
        "They allow unlimited customization",
        "They combine standardized products with discrete output",
        "They eliminate inventory holding",
        "They involve undifferentiated material flow"
      ],
      "answer": "They combine standardized products with discrete output",
      "marks": 2
    },
    {
      "id": "q6",
      "type": "multipleChoice",
      "question": "Which characteristic is UNIQUE to continuous flow processes compared to mass processes?",
      "options": [
        "High production volume",
        "Specialized equipment",
        "Uninterrupted material flow over long periods",
        "Low product variety"
      ],
      "answer": "Uninterrupted material flow over long periods",
      "marks": 2
    },
    {
      "id": "q7",
      "type": "multipleChoice",
      "question": "The product–process matrix primarily helps managers to:",
      "options": [
        "Schedule production more efficiently",
        "Align product volume–variety with appropriate process structures",
        "Determine selling prices",
        "Reduce labor costs directly"
      ],
      "answer": "Align product volume–variety with appropriate process structures",
      "marks": 2
    },
    {
      "id": "q8",
      "type": "multipleChoice",
      "question": "Operating far from the diagonal of the product–process matrix is MOST likely to result in:",
      "options": [
        "Higher efficiency and flexibility",
        "Lower capital investment",
        "Higher costs and operational inefficiencies",
        "Shorter throughput times"
      ],
      "answer": "Higher costs and operational inefficiencies",
      "marks": 2
    },
    {
      "id": "q9",
      "type": "multipleChoice",
      "question": "Which of the following is NOT a primary purpose of a process flowchart?",
      "options": [
        "Identifying bottlenecks",
        "Training employees",
        "Estimating market demand",
        "Improving process efficiency"
      ],
      "answer": "Estimating market demand",
      "marks": 2
    },
    {
      "id": "q10",
      "type": "multipleChoice",
      "question": "High work-in-process inventory usually indicates:",
      "options": [
        "High process efficiency",
        "Balanced capacity across all stages",
        "Presence of bottlenecks or long cycle times",
        "Low throughput time"
      ],
      "answer": "Presence of bottlenecks or long cycle times",
      "marks": 2
    },
    {
      "id": "q11",
      "type": "multipleChoice",
      "question": "According to Little’s Law, throughput time will increase if:",
      "options": [
        "Work-in-process decreases",
        "Cycle time decreases",
        "Work-in-process increases, holding cycle time constant",
        "Output rate increases"
      ],
      "answer": "Work-in-process increases, holding cycle time constant",
      "marks": 2
    },
    {
      "id": "q12",
      "type": "multipleChoice",
      "question": "Which document is MOST useful for understanding the sequence of manufacturing operations?",
      "options": [
        "Assembly drawing",
        "Assembly chart",
        "Routing sheet",
        "Product specification sheet"
      ],
      "answer": "Routing sheet",
      "marks": 2
    },
    {
      "id": "q13",
      "type": "multipleChoice",
      "question": "Break-even analysis is especially valuable in process selection because it:",
      "options": [
        "Eliminates uncertainty in demand",
        "Links cost structure with expected demand volume",
        "Ensures maximum profit at all volumes",
        "Focuses only on variable costs"
      ],
      "answer": "Links cost structure with expected demand volume",
      "marks": 2
    },
    {
      "id": "q14",
      "type": "multipleChoice",
      "question": "A process with high fixed costs and low variable costs is MOST suitable when:",
      "options": [
        "Demand is uncertain and low",
        "Demand volume is expected to be high",
        "Customization requirements are high",
        "Product life cycle is very short"
      ],
      "answer": "Demand volume is expected to be high",
      "marks": 2
    },
    {
      "id": "q15",
      "type": "multipleChoice",
      "question": "The point of indifference between two processes represents:",
      "options": [
        "The profit-maximizing output level",
        "The demand level where total costs are equal",
        "The minimum viable production volume",
        "The maximum capacity of a process"
      ],
      "answer": "The demand level where total costs are equal",
      "marks": 2
    },

    {
      "id": "q16",
      "type": "trueFalse",
      "question": "A batch process always has lower unit costs than a mass process.",
      "answer": false,
      "marks": 1
    },
    {
      "id": "q17",
      "type": "trueFalse",
      "question": "High customer contact generally increases processing costs.",
      "answer": true,
      "marks": 1
    },
    {
      "id": "q18",
      "type": "trueFalse",
      "question": "Continuous processes are suitable for products with frequent design changes.",
      "answer": false,
      "marks": 1
    },

    {
      "id": "q19",
      "type": "fillInBlank",
      "question": "Processes that handle low volume and high variety are typically positioned at the ________ end of the volume–variety continuum.",
      "answer": "low-volume",
      "marks": 2
    },
    {
      "id": "q20",
      "type": "fillInBlank",
      "question": "The mathematical relationship linking throughput time, work-in-process, and cycle time is known as ________ Law.",
      "answer": "Little’s",
      "marks": 2
    },

    {
      "id": "q21",
      "type": "multiSelect",
      "question": "Which factors increase process complexity?",
      "options": ["High variety", "High variation", "Low volume", "Low customer contact"],
      "answer": ["High variety", "High variation", "Low volume"],
      "marks": 3
    },
    {
      "id": "q22",
      "type": "multiSelect",
      "question": "Which process types typically produce to stock?",
      "options": ["Jobbing", "Batch", "Mass", "Continuous"],
      "answer": ["Mass", "Continuous"],
      "marks": 3
    },

    {
      "id": "q23",
      "type": "matching",
      "question": "Match the process type with its typical application.",
      "pairs": [
        { "left": "Project", "right": "Construction of a flyover" },
        { "left": "Jobbing", "right": "Custom jewelry making" },
        { "left": "Batch", "right": "Cosmetics production" },
        { "left": "Mass", "right": "Automobile assembly" }
      ],
      "marks": 4
    },

    {
      "id": "q24",
      "type": "matching",
      "question": "Match each document with its purpose.",
      "pairs": [
        { "left": "Assembly drawing", "right": "Shows how components fit together" },
        { "left": "Assembly chart", "right": "Indicates parts and assembly sequence" },
        { "left": "Routing sheet", "right": "Lists operations and equipment" }
      ],
      "marks": 4
    },

    {
      "id": "q25",
      "type": "shortAnswer",
      "question": "Explain why product design and process design should not be treated as independent decisions.",
      "marks": 3
    },

    {
      "id": "q26",
      "type": "shortAnswer",
      "question": "Why does moving from a job process to a mass process usually reduce unit costs?",
      "marks": 3
    },

    {
      "id": "q27",
      "type": "shortAnswer",
      "question": "Briefly explain how bottlenecks affect throughput time.",
      "marks": 3
    },

    {
      "id": "q28",
      "type": "shortAnswer",
      "question": "Why might a firm deliberately choose a process with higher unit costs?",
      "marks": 3
    },

    {
      "id": "q29",
      "type": "shortAnswer",
      "question": "Explain one risk associated with heavy automation in manufacturing processes.",
      "marks": 3
    },

    {
      "id": "q30",
      "type": "shortAnswer",
      "question": "What distinguishes business process reengineering from continuous improvement?",
      "marks": 3
    },

    {
      "id": "q31",
      "type": "essay",
      "question": "Critically analyze how the volume–variety relationship influences the choice between jobbing, batch, mass, and continuous processes. Use examples to support your answer.",
      "marks": 8
    },

    {
      "id": "q32",
      "type": "essay",
      "question": "Evaluate the role of break-even analysis in selecting among alternative manufacturing processes. Discuss its strengths and limitations in real-world decision making.",
      "marks": 8
    }
  ]
}
